protocol_proxy/__no__init__.py
protocol_proxy/ipc/__init__.py
protocol_proxy/ipc/asyncio.py
protocol_proxy/ipc/base.py
protocol_proxy/ipc/decorator.py
protocol_proxy/ipc/gevent.py
protocol_proxy/ipc/headers.py
protocol_proxy/manager/__init__.py
protocol_proxy/manager/asyncio.py
protocol_proxy/manager/base.py
protocol_proxy/manager/gevent.py
protocol_proxy/proxy/__init__.py
protocol_proxy/proxy/asyncio.py
protocol_proxy/proxy/base.py
protocol_proxy/proxy/gevent.py
protocol_proxy/proxy/launch.py
protocol_proxy-2.0.0rc1.dist-info/LICENSE
protocol_proxy-2.0.0rc1.dist-info/METADATA
protocol_proxy-2.0.0rc1.dist-info/WHEEL
protocol_proxy-2.0.0rc1.dist-info/RECORD
