Metadata-Version: 2.3
Name: protocol-proxy
Version: 2.0.0rc1
Summary: A system for launching and communicating with a proxy application for network communication which runs in a separate process..
License: Apache-2.0
Author: The VOLTTRON Development Team
Author-email: volttron@pnnl.gov
Requires-Python: >=3.10,<4.0
Classifier: Intended Audience :: Developers
Classifier: Intended Audience :: Information Technology
Classifier: Intended Audience :: Other Audience
Classifier: Intended Audience :: Science/Research
Classifier: License :: OSI Approved :: Apache Software License
Classifier: Programming Language :: Python :: 3
Classifier: Programming Language :: Python :: 3.10
Classifier: Programming Language :: Python :: 3.11
Classifier: Programming Language :: Python :: 3.12
Classifier: Programming Language :: Python :: 3.13
Classifier: Programming Language :: Python :: 3 :: Only
Project-URL: Homepage, https://github.com/eclipse-volttron/lib-protocol-proxy
Project-URL: Repository, https://github.com/eclipse-volttron/lib-protocol-proxy
